[
  {
    "anonymous": false,
    "inputs": [
      {
        "indexed": true,
        "internalType": "address",
        "name": "creator",
        "type": "address"
      },
      {
        "indexed": true,
        "internalType": "address",
        "name": "split",
        "type": "address"
      }
    ],
    "name": "createdSplit",
    "type": "event"
  },
  {
    "inputs": [
      {
        "internalType": "address[]",
        "name": "payees",
        "type": "address[]"
      },
      {
        "internalType": "uint256[]",
        "name": "shares",
        "type": "uint256[]"
      }
    ],
    "name": "createSplit",
    "outputs": [
      {
        "internalType": "address",
        "name": "",
        "type": "address"
      }
    ],
    "stateMutability": "nonpayable",
    "type": "function"
  },
  {
    "inputs": [
      {
        "internalType": "address",
        "name": "",
        "type": "address"
      }
    ],
    "name": "splitsDatabase",
    "outputs": [
      {
        "internalType": "uint256",
        "name": "totalSplits",
        "type": "uint256"
      }
    ],
    "stateMutability": "view",
    "type": "function"
  }
]
